{
  "url": "https://www.mymomshomecooking.com/post/grilled-maple-glazed-herbed-salmon-with-pineapple-salsa",
  "slug": "grilled-maple-glazed-herbed-salmon-with-pineapple-salsa",
  "title": "Grilled Maple Glazed Herbed Salmon with Pineapple Salsa",
  "serves": "",
  "category": "Seafood",
  "date": "2022-02-26",
  "ingredients": [
    "Serves 4",
    "**Salmon**",
    "4 6oz salmon fillets, no skin",
    "1 tsp paprika",
    "1 tsp chili powder",
    "\u00bc tsp sugar",
    "1 tsp kosher salt",
    "4 tbsp 100% maple syrup",
    "**Salsa**",
    "3 cups diced fresh pineapple",
    "2 tablespoons fresh chopped cilantro",
    "1 \u00bd tbsp 100% maple syrup"
  ],
  "instructions": "In a medium bowl combine all the salsa ingredients and set aside.\nMix the paprika, chili powder, salt and sugar together in a small bowl.\nPlace the salmon in a baking dish and coat with the spice mixture. Cook on an oiled grill, for 6-8 minutes or until almost done; brush with the maple syrup and continue cooking until done.\nRemove the salmon from the grill and serve with the salsa as a garnish. Serve the remaining salsa in a bowl for additional garnish if desired.",
  "images": [],
  "local_image": "/Users/remibarton/Documents/mom-recipe-scrape/output/images/grilled-maple-glazed-herbed-salmon-with-pineapple-salsa.png"
}