{
  "url": "https://www.mymomshomecooking.com/post/homemade-coleslaw",
  "slug": "homemade-coleslaw",
  "title": "Homemade Coleslaw",
  "serves": "",
  "category": "Salads",
  "date": "2022-02-26",
  "ingredients": [
    "1 16oz bag coleslaw mix(with red cabbage)",
    "2 tbsp onion, diced",
    "2/3 cup Miracle Whip",
    "3 tbsp vegetable oil",
    "\u00bd cup sugar",
    "1 tbsp white vinegar",
    "\u00bd tsp Kosher salt",
    "\u00bd tsp poppy seeds"
  ],
  "instructions": "In a small mixing bowl whisk together the Miracle Whip, vegetable oil, sugar, vinegar, salt and poppy seeds. Set aside.\nIn a medium bowl combine the coleslaw mix and the onion and toss. Season to taste with salt and pepper.\nAdd half of the dressing and refrigerate for several hours. The coleslaw will become too soupy if you add all the dressing before you refrigerate. Add more dressing if desired after refrigeration. (we prefer a dryer coleslaw)",
  "images": [],
  "local_image": "/Users/remibarton/Documents/mom-recipe-scrape/output/images/homemade-coleslaw.jpg"
}