{
  "url": "https://www.mymomshomecooking.com/post/honey-sriracha-sauce",
  "slug": "honey-sriracha-sauce",
  "title": "Honey Sriracha Sauce",
  "serves": "",
  "category": "Gravy, Sauce & Dressing",
  "date": "2022-02-26",
  "ingredients": [
    "\u00bc cup honey",
    "2 tsp soy sauce",
    "4 tsp fresh lime juice",
    "1 tbsp fresh sliced cilantro stems"
  ],
  "instructions": "Place all the ingredients in a small bowl and whisk together until well blended. Place in a small serving bowl and chill until ready to serve.",
  "images": [],
  "local_image": "/Users/remibarton/Documents/mom-recipe-scrape/output/images/honey-sriracha-sauce.png"
}