{
  "url": "https://www.mymomshomecooking.com/post/raspberry-brie-bites-makes-12",
  "slug": "raspberry-brie-bites-makes-12",
  "title": "Raspberry Brie Bites",
  "serves": "Makes 12",
  "category": "Appetizers & Dips",
  "date": "2022-02-27",
  "ingredients": [
    "12 wonton wraps",
    "buttery cooking spray",
    "8 ounces Brie, rind removed",
    "1/4 cup raspberry preserves",
    "fresh raspberries (frozen if in a pinch)"
  ],
  "instructions": "Preheat oven to 375\u00ba.\nLightly spray 12 slots of mini muffin tin with cookie spray. Insert one wonton skin in each slot, forming a cup.\nCut brie into pieces that will fit into bottom of each cup.\nTop each piece of brie with \u00bc tsp of raspberry preserves.\nPlace a fresh raspberry inside of each wonton.\nBake for 10-12 minutes or till shells are nicely browned.\nNote: you can save the fresh raspberry placement until after baking if preferred",
  "images": [],
  "local_image": "/Users/remibarton/Documents/mom-recipe-scrape/output/images/raspberry-brie-bites-makes-12.png"
}