{
  "url": "https://www.mymomshomecooking.com/post/zuppa-toscana",
  "slug": "zuppa-toscana",
  "title": "Zuppa Toscana",
  "serves": "",
  "category": "Soup & Sandwiches",
  "date": "2022-02-28",
  "ingredients": [
    "1lb Italian sausage, \u00bd sweet \u00bd hot, skin removed",
    "3 medium potatoes, peeled and chopped",
    "\u00bd large Vidalia onion, chopped",
    "\u00bc cup cooked and crumbled bacon",
    "4 cloves garlic, minced",
    "32oz chicken broth",
    "1 cup chopped kale",
    "1 cup heavy cream",
    "2 tbsp flour",
    "Salt and pepper",
    "cayenne"
  ],
  "instructions": "Brown the sausage in a skillet, breaking it up(not too small) as it browns.\nPlace the cooked sausage, chicken broth, garlic, potatoes and onion in a crockpot and add just enough water to cover the ingredients. Cook on high for 4 hours (low for 6) until the potatoes are tender.\nWith 30 minutes left to cook, mix the flour with the cream, whisking to remove any lumps. Add to the soup.\nAdd the kale and the bacon and stir. Cook on high for 30 minutes or until the soup has thickened. Add the seasonings to taste.",
  "images": [],
  "local_image": "/Users/remibarton/Documents/mom-recipe-scrape/output/images/zuppa-toscana.png"
}